{
  "schemaVersion": 1,
  "preset": "cmdShiftCtrl",
  "launchAtLogin": false,
  "bindings": {
    "inputHDMI1": [
      {
        "mods": [
          "control",
          "alt",
          "shift"
        ],
        "key": "H"
      }
    ],
    "inputHDMI2": [
      {
        "mods": [
          "control",
          "alt",
          "shift"
        ],
        "key": "J"
      }
    ],
    "inputTypeC": [
      {
        "mods": [
          "control",
          "alt",
          "shift"
        ],
        "key": "C"
      }
    ],
    "inputDP": [
      {
        "mods": [
          "control",
          "alt",
          "shift"
        ],
        "key": "D"
      }
    ],
    "kvmUSBC": [
      {
        "mods": [
          "control",
          "alt",
          "shift"
        ],
        "key": "K"
      }
    ],
    "kvmUpstream": [
      {
        "mods": [
          "control",
          "alt",
          "shift"
        ],
        "key": "U"
      }
    ],
    "kvmAuto": [
      {
        "mods": [
          "control",
          "alt",
          "shift"
        ],
        "key": "A"
      }
    ],
    "pbpOff": [
      {
        "mods": [
          "control",
          "alt",
          "shift"
        ],
        "key": "O"
      }
    ],
    "pbpPIP": [
      {
        "mods": [
          "control",
          "alt",
          "shift"
        ],
        "key": "I"
      }
    ],
    "pbpOn": [
      {
        "mods": [
          "control",
          "alt",
          "shift"
        ],
        "key": "P"
      }
    ],
    "showLauncher": [
      {
        "mods": [
          "control",
          "alt",
          "shift"
        ],
        "key": "Space"
      }
    ]
  },
  "altGrAvoidList": {
    "keys": [
      "Q",
      "E",
      "B",
      "7",
      "2",
      "3",
      "4",
      "5",
      "8",
      "9",
      "0"
    ],
    "note": "Letters/digits that commonly carry an AltGr-composed char on EU layouts (e.g. @, EUR, {, }, [, ], accented vowels). Advisory only."
  },
  "edgeSwitchEnabled": false
}
